[
    {
        "title": "Capricciosa Pizza",
        "imageUrlS": "https://drive.google.com/uc?export=download&id=1L7x91k3MRUZOKG9f5UpetdFbjbUXAefF",
        "imageUrl": "https://drive.google.com/uc?export=download&id=1urJq4UlVXkmYsEujGS4CUs-Oeqtg3SfT",
        "price": "12.99",
        "ingredients": "Ham, mushrooms, artichokes, olives, mozzarella, tomato sauce",
        "description": "Classic Italian Capricciosa pizza with ham, mushrooms, artichokes, and olives."
    },
    {
        "title": "Amour Pizza",
        "imageUrlS": "https://drive.google.com/uc?export=download&id=1FqKiJEWiVJkXk_CySryONgthQbkCBsxr",
        "imageUrl": "https://drive.google.com/uc?export=download&id=18Ot89aWGM7BLutn3FViTMFWjP48eRDbE",
        "price": "14.99",
        "ingredients": "Shrimps, strawberries, basil, mozzarella, tomato sauce",
        "description": "Amour Pizza, a delightful combination of shrimps, strawberries and fresh basil."
    },
    {
        "title": "Seafood Pizza",
        "imageUrlS": "https://drive.google.com/uc?export=download&id=1WPG4FwLHKTf7NNghqsUR1LxHCVJfMCg9",
        "imageUrl": "https://drive.google.com/uc?export=download&id=1OdtwbA2GazlAusp_4m_DA5sE50umJa3c",
        "price": "16.99",
        "ingredients": "Shrimp, squid, mussels, clams, garlic, mozzarella, white sauce",
        "description": "Delicious Seafood Pizza loaded with shrimp, squid, mussels, and clams."
    },
    {
        "title": "Three Seas Pizza",
        "imageUrlS": "https://drive.google.com/uc?export=download&id=1gdcBCxwfuxkGL3EeDEKpYKY6DC6u9j8o",
        "imageUrl": "https://drive.google.com/uc?export=download&id=1-nMurdFwVRMHFj2H4b5DcCd9juEu9u_Q",
        "price": "15.99",
        "ingredients": "Tuna, anchovies, shrimp, garlic, capers, mozzarella, tomato sauce",
        "description": "Three Seas Pizza featuring tuna, anchovies, and shrimp for a taste of the sea."
    },
    {
        "title": "Dessert Pizza",
        "imageUrlS": "https://drive.google.com/uc?export=download&id=1-kMs7RCtSC_KRIh4hcEj8x8s99_NKhig",
        "imageUrl": "https://drive.google.com/uc?export=download&id=1eMcytcBPRZgoiFIGSKaVRczc8MG51Lkv",
        "price": "10.99",
        "ingredients": "Nutella, M&M's, bananas, powdered sugar, mozzarella",
        "description": "Indulge in our Dessert Pizza topped with Nutella and bananas."
    },
    {
        "title": "Hunter Pizza",
        "imageUrlS": "https://drive.google.com/uc?export=download&id=1OJLX2TDcXMZ8wnyAKJVW7dQIRZRHDcU5",
        "imageUrl": "https://drive.google.com/uc?export=download&id=1Jjo3viEIQcGUL7Iid4PPkfA1IGRpLAKV",
        "price": "13.99",
        "ingredients": "Venison, mushrooms, caramelized onions, blue cheese, mozzarella, tomato sauce",
        "description": "Savor the flavors of the forest with our Hunter Pizza featuring venison, mushrooms, and caramelized onions."
    },
    {
        "title": "Meat Pizza",
        "imageUrlS": "https://drive.google.com/uc?export=download&id=13A6GRIQL-6RSW-2DkiGg3Ccst_657N7u",
        "imageUrl": "https://drive.google.com/uc?export=download&id=18aDE9n6sJMKvjNQSU6MC2wYFwfbZTgoD",
        "price": "11.99",
        "ingredients": "Pepperoni, sausage, bacon, ham, ground beef, mozzarella, tomato sauce",
        "description": "For meat lovers, our Meat Pizza is loaded with pepperoni, sausage, bacon, ham, and ground beef."
    },
    {
        "title": "Bolognese Pizza",
        "imageUrlS": "https://drive.google.com/uc?export=download&id=1v0cXpBvQKWvQyMOr1cbRwESEnspbjW0j",
        "imageUrl": "https://drive.google.com/uc?export=download&id=1ya1B0_zzJPEgwsQUP4RmvPs6IcbSkSCE",
        "price": "14.99",
        "ingredients": "Ground beef, mozzarella, Bolognese sauce",
        "description": "Enjoy the hearty flavors of our classic Bolognese Pizza with ground beef and mozzarella."
    },
    {
        "title": "Caesar Pizza",
        "imageUrlS": "https://drive.google.com/uc?export=download&id=1a1V-qOJbGh9_lwS6MWMMj3Y9GPSh-D_e",
        "imageUrl": "https://drive.google.com/uc?export=download&id=1k8lmCsC7RrxLhTs30Tlu7ZWjWn_vdROY",
        "price": "12.99",
        "ingredients": "Grilled chicken, romaine lettuce, Parmesan cheese, Caesar dressing",
        "description": "A twist on the classic Caesar salad, our Caesar Pizza features grilled chicken, romaine lettuce, and Parmesan cheese."
    },
    {
        "title": "Village Pizza",
        "imageUrlS": "https://drive.google.com/uc?export=download&id=1aGu9Ty6ApfDq1ZkvUtf9HzqypGtXUsNV",
        "imageUrl": "https://drive.google.com/uc?export=download&id=1tQ-gjI6FW1Flx-bPb6dyL5ENXj2IWRFe",
        "price": "13.99",
        "ingredients": "Italian sausage, roasted red peppers, caramelized onions, feta cheese, mozzarella, tomato sauce",
        "description": "Experience the flavors of a rustic village with our Village Pizza, featuring Italian sausage, roasted red peppers, and caramelized onions."
    },
    {
        "title": "Hawaiian Pizza",
        "imageUrlS": "https://drive.google.com/uc?export=download&id=1SJexW6nbO6aMRkMEaf_p59wghq5ikJN9",
        "imageUrl": "https://drive.google.com/uc?export=download&id=1A5CgIAsaYcTjfksdoMzQl5ZcKN_JY_Av",
        "price": "11.99",
        "ingredients": "Ham, pineapple, bacon, mozzarella, tomato sauce",
        "description": "Taste the tropics with our Hawaiian Pizza, topped with ham, pineapple, and bacon."
    },
    {
        "title": "Pepperoni Mushroom Pizza",
        "imageUrlS": "https://drive.google.com/uc?export=download&id=16LRwkHxsDzZn_eAw8yHqH52uOH-E04wW",
        "imageUrl": "https://drive.google.com/uc?export=download&id=159tAVK4KSnUhn9Tk5r1RX5x74FVIOkXa",
        "price": "10.99",
        "ingredients": "Pepperoni, mushrooms, mozzarella, tomato sauce",
        "description": "Classic Pepperoni Mushroom Pizza loaded with pepperoni and mushrooms."
    },
    {
        "title": "Chicken Pizza",
        "imageUrlS": "https://drive.google.com/uc?export=download&id=12uCwvopvmvg4IdPLsFxtbgbnGhs4owST",
        "imageUrl": "https://drive.google.com/uc?export=download&id=1mTw1vDtah2h49IMMT0HQgXNCwa6tFjjk",
        "price": "12.99",
        "ingredients": "Grilled chicken, barbecue sauce, red onions, cilantro, mozzarella",
        "description": "Satisfy your cravings with our Chicken Pizza, featuring grilled chicken, barbecue sauce, and red onions."
    },
    {
        "title": "Pepperoni Pizza",
        "imageUrlS": "https://drive.google.com/uc?export=download&id=1SUsfpQE7BhWeZJEpyJotwzcTi0DmOjn1",
        "imageUrl": "https://drive.google.com/uc?export=download&id=1y5eAEopCwHLgFw3PrAWcUTy6pY51qm7h",
        "price": "9.99",
        "ingredients": "Pepperoni, mozzarella, tomato sauce",
        "description": "Classic Pepperoni Pizza loaded with spicy pepperoni slices."
    },
    {
        "title": "Favorite Pizza",
        "imageUrlS": "https://drive.google.com/uc?export=download&id=1shyD1TLfMuuGJQr73A3LsRsrtVYBDEXf",
        "imageUrl": "https://drive.google.com/uc?export=download&id=1gQBA7GufFNgmE0NXJHFqW4g6pykngnJ8",
        "price": "13.99",
        "ingredients": "Bacon, sausage, mushrooms, bell peppers, onions, olives, mozzarella, tomato sauce",
        "description": "Our Favorite Pizza is a crowd-pleaser with bacon, sausage, mushrooms, and bell peppers."
    },
    {
        "title": "Veggie Pizza",
        "imageUrlS": "https://drive.google.com/uc?export=download&id=18RO_AgFfWbuIe8svJ2u-5Tah7LsHaAcY",
        "imageUrl": "https://drive.google.com/uc?export=download&id=1NNzBNeUHzJVMBJpWQTp2vHvMQtpFsAU5",
        "price": "12.99",
        "ingredients": "Spinach, tomatoes, onions, bell peppers, mushrooms, black olives, mozzarella, tomato sauce",
        "description": "For vegetarians, our Veggie Pizza is loaded with spinach, tomatoes, onions, and bell peppers."
    },
    {
        "title": "Marinara Pizza",
        "imageUrlS": "https://drive.google.com/uc?export=download&id=120iqsXTSOtg-WKs-Dbba_chrXbVTOO-d",
        "imageUrl": "https://drive.google.com/uc?export=download&id=1rSqqZNlJS1Bbf1I6QM8ra7tt1af4XLE_",
        "price": "9.99",
        "ingredients": "Garlic, oregano, basil, olive oil, Tofu cheese, tomato sauce",
        "description": "Simple yet delicious, our Marinara Pizza is topped with garlic, oregano, and basil."
    },
    {
        "title": "Ham Mushroom Pizza",
        "imageUrlS": "https://drive.google.com/uc?export=download&id=1qpr3EaOtMnfg4CYL9lQ966PQHMCVup-Y",
        "imageUrl": "https://drive.google.com/uc?export=download&id=1UcyYyRZLNIXRAVfUbaTEn4xVchEo050G",
        "price": "11.99",
        "ingredients": "Ham, mushrooms, mozzarella, tomato sauce",
        "description": "Classic combination of ham and mushrooms on our Ham Mushroom Pizza."
    },
    {
        "title": "Four Cheese Pizza",
        "imageUrlS": "https://drive.google.com/uc?export=download&id=1m1S6BMO7JzatDAhKxnvNuHaBiA3zJQoX",
        "imageUrl": "https://drive.google.com/uc?export=download&id=1SrS_fDlYddVDsHYdJH4fOgzi10flIgLt",
        "price": "12.99",
        "ingredients": "Mozzarella, Parmesan, cheddar, feta, tomato sauce",
        "description": "Indulge in our Four Cheese Pizza loaded with Mozzarella, Parmesan, cheddar, and feta."
    },
    {
        "title": "Margherita Pizza",
        "imageUrlS": "https://drive.google.com/uc?export=download&id=1qQMZEto-waoOVzFmvQ0prvdd7T2-edNG",
        "imageUrl": "https://drive.google.com/uc?export=download&id=14UYPhfjLal4Gm8u-gRxSfp8wS_krc-Wx",
        "price": "10.99",
        "ingredients": "Tomatoes, fresh mozzarella, basil, olive oil, tomato sauce",
        "description": "Traditional Margherita Pizza topped with fresh tomatoes, mozzarella, and basil."
    }
]
